setup.py
matfactor/__init__.py
matfactor/_factorize.pyx
matfactor.egg-info/PKG-INFO
matfactor.egg-info/SOURCES.txt
matfactor.egg-info/dependency_links.txt
matfactor.egg-info/requires.txt
matfactor.egg-info/top_level.txt